webhdfsmagic/__init__.py
webhdfsmagic/client.py
webhdfsmagic/config.py
webhdfsmagic/install.py
webhdfsmagic/logger.py
webhdfsmagic/magics.py
webhdfsmagic/utils.py
webhdfsmagic/commands/__init__.py
webhdfsmagic/commands/base.py
webhdfsmagic/commands/directory_ops.py
webhdfsmagic/commands/file_ops.py
webhdfsmagic/commands/permission_ops.py
webhdfsmagic-0.0.2.dist-info/licenses/LICENSE
webhdfsmagic-0.0.2.dist-info/METADATA
webhdfsmagic-0.0.2.dist-info/WHEEL
webhdfsmagic-0.0.2.dist-info/entry_points.txt
webhdfsmagic-0.0.2.dist-info/top_level.txt
webhdfsmagic-0.0.2.dist-info/RECORD
