Metadata-Version: 2.4
Name: webhdfsmagic
Version: 0.0.2
Summary: IPython magic commands to interact with HDFS via WebHDFS/Knox
Author-email: ab2dridi  <a-d13@hotmail.fr>
License-Expression: MIT
Classifier: Programming Language :: Python :: 3
Requires-Python: >=3.9
License-File: LICENSE
Requires-Dist: requests>=2.20.0
Requires-Dist: pandas>=1.0.0
Requires-Dist: traitlets>=4.3.0
Requires-Dist: ipython>=7.0.0
Requires-Dist: jupyter_core>=4.0.0
Provides-Extra: dev
Requires-Dist: pytest>=5.0.0; extra == "dev"
Requires-Dist: pytest-cov>=4.0.0; extra == "dev"
Requires-Dist: ruff>=0.1.0; extra == "dev"
Dynamic: license-file
